{
    "last_id": 5,
    "abonati":[
{
    "id":0,
    "nume":"Ana",
    "descriere": "Ambitios, un baiat curajos",
    "inaltime": 175,
    "baiat":"true",
    "dataInreg": "2019-09-22T13:37:56.920Z",
    "Obiective": "mentinere,regim,sala",
    "vizite la sala(ultima luna": "10",
    "kg":70
},
{
    "id":1,
    "nume":"Albert David ",
    "descriere": "grasut, ii place sa bage mc donalds",
    "inaltime": 195,
    "baiat":"true",
    "dataInreg": "2019-09-22T13:23:56.920Z",
    "Obiective": "mentinere,regim,sala,slabire",
    "vizite la sala(ultima luna": "13",
    "kg":60
},
{
    "id":2,
    "nume":"Dan Nimara",
    "descriere": "delasator,bere,petrecaret",
    "inaltime": 175,
    "baiat":"true",
    "dataInreg": "2019-09-22T13:37:34.920Z",
    "Obiective": "ingrasare,regim,sala",
    "vizite la sala(ultima luna": "6",
    "kg":80
},
{
    "id":3,
    "nume":"Dima Oana",
    "descriere": "muncitoare,corgi",
    "inaltime": 170,
    "baiat":"false",
    "dataInreg": "2019-09-22T13:31:56.920Z",
    "Obiective": "sala,crestere nasa musculara,sport",
    "vizite la sala(ultima luna": "13",
    "kg": 75
},
{
    "id":4,
    "nume":"Bertalan Victor",
    "descriere": "curajos,puternic,devodat",
    "inaltime": 179,
    "baiat":"true",
    "dataInreg": "2019-09-22T13:37:56.920Z",
    "Obiective": "slabit,regim,sala",
    "vizite la sala(ultima luna": "20",
    "kg": 72
},
{
    "id":5,
    "nume":"Cornel Dana",
    "descriere": "muncitor harnic",
    "inaltime": 175,
    "baiat":"true",
    "dataInreg": "2020-09-22T13:31:56.920Z",
    "Obiective": "crestere nasa musculara,sport",
    "vizite la sala(ultima luna": "1",
    "kg":80
},
{
    "id":6,
    "nume":"Codrin Bradea",
    "descriere": "lenes puternic",
    "inaltime": 182,
    "baiat":"true",
    "dataInreg": "2020-12-22T13:31:56.920Z",
    "Obiective": "slabire",
    "vizite la sala(ultima luna": "13",
    "kg": 60
},
{
    "id":7,
    "nume":"Nicula Codrut",
    "descriere": "stresat muncitor",
    "inaltime": 181,
    "baiat":"true",
    "dataInreg": "2020-12-22T11:31:56.920Z",
    "Obiective": "mentinere",
    "vizite la sala(ultima luna": "11",
    "kg": 68
},
{
    "id":8,
    "nume":"Caragiale Dorina",
    "descriere": "ambitioasa",
    "inaltime": 162,
    "baiat":"false",
    "dataInreg": "2020-12-22T14:12:56.920Z",
    "Obiective": "slabire mentinere",
    "vizite la sala(ultima luna": "4",
    "kg":55
},
{
    "id":9,
    "nume":"Caragiale Alex",
    "descriere": "carismatic atlet",
    "inaltime": 193,
    "baiat":"true",
    "dataInreg": "2014-12-21T11:14:55.920Z",
    "Obiective": "slabire ",
    "vizite la sala(ultima luna": "23",
    "kg":65
},
{
    "id":10,
    "nume":"Cicaldau Florina",
    "descriere": "lenesa",
    "inaltime": 154,
    "baiat":"false",
    "dataInreg": "2019-10-21T13:11:52.920Z",
    "Obiective": " mentinere",
    "vizite la sala(ultima luna": "2",
    "kg":""
},
{
    "id":11,
    "nume":"Ana",
    "descriere": "lenes",
    "inaltime": 154,
    "baiat":"true",
    "dataInreg": "2018-04-14T12:11:56.920Z",
    "Obiective": "ingrasare",
    "vizite la sala(ultima luna": "6",
    "kg":89
},
{
    "id":12,
    "nume":"Cochilet Teodor",
    "descriere": "delasator",
    "inaltime": 172,
    "baiat":"true",
    "dataInreg": "2019-08-13T10:12:56.920Z",
    "Obiective": "slabire",
    "vizite la sala(ultima luna": "1",
    "kg":67
},
{
    "id":13,
    "nume":"Dormeanu Anca",
    "descriere": "muncitoare",
    "inaltime": 164,
    "baiat":"false",
    "dataInreg": "2017-02-22T08:12:56.920Z",
    "Obiective": "mentinere",
    "vizite la sala(ultima luna": "14",
    "kg":54
},
{
    "id":14,
    "nume":"Silistru Alex",
    "descriere": "ambitioas",
    "inaltime": 174,
    "baiat":"true",
    "dataInreg": "2019-05-12T23:12:56.920Z",
    "Obiective": "slabire",
    "vizite la sala(ultima luna": "9",
    "kg":88
}
]

}